spatial_image_multiscale.py
spatial_image_multiscale-0.4.2.dist-info/LICENSE
spatial_image_multiscale-0.4.2.dist-info/WHEEL
spatial_image_multiscale-0.4.2.dist-info/METADATA
spatial_image_multiscale-0.4.2.dist-info/RECORD
