Metadata-Version: 2.1
Name: spatial_image_multiscale
Version: 0.4.2
Summary: spatial-image-multiscale
Home-page: https://github.com/spatial-image/spatial-image-multiscale
Author: Matt McCormick
Author-email: matt.mccormick@kitware.com
Classifier: License :: OSI Approved :: Apache Software License
Requires-Dist: numpy
Requires-Dist: dask
Requires-Dist: xarray
Requires-Dist: xarray-datatree
Requires-Dist: spatial_image>=0.2.1
Requires-Dist: itk-filtering>=5.3rc4 ; extra == "test"
Requires-Dist: jsonschema ; extra == "test"
Requires-Dist: pytest ; extra == "test"
Requires-Dist: pytest-mypy ; extra == "test"
Requires-Dist: fsspec ; extra == "test"
Requires-Dist: ipfsspec ; extra == "test"
Requires-Dist: nbmake ; extra == "test"
Requires-Dist: zarr ; extra == "test"
Provides-Extra: test
